nscrap/__init__.py
nscrap/container.py
nscrap/keywords.py
nscrap/messenger.py
nscrap/press.py
nscrap/runner.py
nscrap/scraper.py
tests/__init__.py
tests/test_runner.py
nscrap-0.0.4.dist-info/LICENSE
nscrap-0.0.4.dist-info/METADATA
nscrap-0.0.4.dist-info/WHEEL
nscrap-0.0.4.dist-info/top_level.txt
nscrap-0.0.4.dist-info/RECORD
