Metadata-Version: 2.1
Name: nscrap
Version: 0.0.4
Summary: Articles notification by scheduled web scrapers
Home-page: https://github.com/pparkddo/nscrap
Author: pparkddo
Author-email: ehdud3453@gmail.com
License: UNKNOWN
Platform: UNKNOWN
Classifier: Programming Language :: Python :: 3
Classifier: License :: OSI Approved :: GNU General Public License v3 (GPLv3)
Classifier: Operating System :: OS Independent
Requires-Python: >=3.7
Requires-Dist: APScheduler
Requires-Dist: python-telegram-bot
